{
  "type": "Microsoft.Authorization/policyDefinitions",
  "apiVersion": "2023-04-01",
  "name": "Deny-Aks-CSI",
  "properties": {
    "displayName": "Azure Kubernetes Clusters should enable Key Management Service (KMS)",
    "mode": "Indexed",
    "policyType": "Custom",
    "description": "Use Key Management Service (KMS) to encrypt secret data at rest in etcd for Kubernetes cluster security. Learn more at: https://aka.ms/aks/kmsetcdencryption.",
    "metadata": {
      "version": "1.0.0",
      "category": "Kubernetes"
    },
    "parameters": {
      "effect": {
        "type": "String",
        "metadata": {
          "displayName": "Effect",
          "description": "Enable or disable the execution of the policy",
          "portalReview": true
        },
        "allowedValues": [
          "Audit",
          "Deny",
          "Disabled"
        ],
        "defaultValue": "Audit"
      }
    },
    "policyRule": {
      "if": {
        "allOf": [
          {
            "field": "type",
            "equals": "Microsoft.ContainerService/managedClusters"
          },
          {
            "field": "identity.type",
            "notEquals": "SystemAssigned"
          },
          {
            "field": "Microsoft.ContainerService/managedClusters/securityProfile.azureKeyVaultKms.enabled",
            "notEquals": true
          }
        ]
      },
      "then": {
        "effect": "[parameters('effect')]"
      }
    }
  }
}
