{
  "type": "Microsoft.Authorization/policyDefinitions",
  "apiVersion": "2023-04-01",
  "name": "Deny-Aks-Cni",
  "properties": {
    "displayName": "Azure Kubernetes Clusters should use Azure CNI",
    "mode": "Indexed",
    "policyType": "Custom",
    "description": "Azure CNI is a prerequisite for some Azure Kubernetes Service features, including Azure network policies, Windows node pools and virtual nodes add-on. Learn more at: https://aka.ms/aks-azure-cni",
    "metadata": {
      "version": "1.0.1",
      "category": "Kubernetes"
    },
    "parameters": {
      "effect": {
        "type": "String",
        "metadata": {
          "displayName": "Effect",
          "description": "Enable or disable the execution of the policy",
          "portalReview": true
        },
        "allowedValues": [
          "Audit",
          "Deny",
          "Disabled"
        ],
        "defaultValue": "Audit"
      }
    },
    "policyRule": {
      "if": {
        "allOf": [
          {
            "field": "type",
            "equals": "Microsoft.ContainerService/managedClusters"
          },
          {
            "field": "Microsoft.ContainerService/managedClusters/networkProfile.networkPlugin",
            "notEquals": "azure"
          }
        ]
      },
      "then": {
        "effect": "[parameters('effect')]"
      }
    }
  }
}
